{
    "siteId": 93161,
    "scanId": 10,
    "pageId": 0,
    "scanFinishTime": "1970-01-01T00:05:19.745Z",
    "scanStartTime": "1969-12-31T23:59:53.291Z",
    "versionCode": "51a7c61a",
    "subUrls": [],
    "pageStatus": "ok/channeltimeout",
    "jobTrace": "93161_10-0 #1dhh7t11yejnpwfzt @51a7c61a",
    "extraPages": [],
    "parts": [{
        "id": "1",
        "type": "Main",
        "parentId": "undefined",
        "address": "https://www.fivebelow.com",
        "properties": [],
        "hasLocation": true,
        "origin": "https://www.fivebelow.com",
        "actions": [{
                "actionId": "kp8771h3jvczt7ka",
                "type": "html/script",
                "start": 1442,
                "duration": 0,
                "data": null
            },
            {
                "actionId": "1jzqrkdp1wpr31we",
                "type": "html/script",
                "start": 1807,
                "duration": 0,
                "data": null
            },
            {
                "actionId": "eu1lopfx6uq29gs",
                "type": "html/script",
                "start": 1809,
                "duration": 0,
                "data": null
            },
            {
                "actionId": "bxusky75cyu5msy",
                "type": "html/script",
                "start": 1811,
                "duration": 0,
                "data": null
            },
            {
                "actionId": "6alur1fpna3esz6p",
                "type": "html/img",
                "start": 2308,
                "duration": 0,
                "data": "https://res.cloudinary.com/dlwdq84ig/image/upload/v1686491497/ghthcwhsztifn87jg7qq.svg"
            },
            {
                "actionId": "desm81ahhf91j7fj4",
                "type": "html/link",
                "start": 2302,
                "duration": 0,
                "data": "https://www.fivebelow.com/_next/static/css/df1e8eca64fa1c66.css"
            },
            {
                "actionId": "17w2jl120gbc19vino",
                "type": "html/link",
                "start": 2289,
                "duration": 0,
                "data": "https://www.fivebelow.com/_next/static/css/198869ad179b776e.css"
            },
            {
                "actionId": "iyio71n09j7ihz02",
                "type": "html/script",
                "start": 2244,
                "duration": 0,
                "data": "https://try.abtasty.com/511d9cc349be07008ab7c7c1d5ffbf6d.js"
            },
            {
                "actionId": "anhnb0oew16jb5u",
                "type": "html/script",
                "start": 3830,
                "duration": 0,
                "data": "https://cdn.cookielaw.org/scripttemplates/otSDKStub.js"
            },
            {
                "actionId": "15y07q1i492c13n30c",
                "type": "html/script",
                "start": 3909,
                "duration": 0,
                "data": "https://www.fivebelow.com/scripts/cookieEventDispatcher.js"
            },
            {
                "actionId": "19kuvvbnfxyxo5oq",
                "type": "html/script",
                "start": 3965,
                "duration": 0,
                "data": "https://www.fivebelow.com/_next/static/chunks/5982-d44b0461d354a6ef.js"
            },
            {
                "actionId": "v7acm6gihf3aa5",
                "type": "html/script",
                "start": 3991,
                "duration": 0,
                "data": "https://www.fivebelow.com/_next/static/chunks/9543-263567822a6f00b2.js"
            },
            {
                "actionId": "h4fhg1gf04d12mllc",
                "type": "html/script",
                "start": 3993,
                "duration": 0,
                "data": "https://www.fivebelow.com/_next/static/chunks/pages/%5B%5B...slug%5D%5D-75f4ddfc7ad8f2fe.js"
            },
            {
                "actionId": "12dl1gyx5yk1bsgs0",
                "type": "html/script",
                "start": 4001,
                "duration": 0,
                "data": "https://www.fivebelow.com/_next/static/vh5esO5bV2XE5vorjQQ3s/_buildManifest.js"
            },
            {
                "actionId": "x1csk1648qwn0zhw",
                "type": "html/script",
                "start": 4008,
                "duration": 0,
                "data": "https://www.fivebelow.com/_next/static/vh5esO5bV2XE5vorjQQ3s/_ssgManifest.js"
            },
            {
                "actionId": "1g6l49dfhfz4ig5h",
                "type": "html/script",
                "start": 3880,
                "duration": 0,
                "data": "https://maps.googleapis.com/maps/api/js?key=AIzaSyBdVm17V1Jp4tu0MINv8gfNnvrBLlU5pyw&libraries=geometry,places"
            },
            {
                "actionId": "1gqvb5lsijtr5v6",
                "type": "html/script",
                "start": 4015,
                "duration": 0,
                "data": "https://www.fivebelow.com/_Incapsula_Resource?SWJIYLWA=719d34d31c8e3a6e6fffd425f7e032f3&ns=1&cb=1455088927"
            },
            {
                "actionId": "pn7uh12shhux4jjz",
                "type": "html/script",
                "start": 3920,
                "duration": 0,
                "data": "https://www.fivebelow.com/_next/static/chunks/1911.abd66340c683b06b.js"
            },
            {
                "actionId": "1balzhrm0nv1i55jl",
                "type": "html/script",
                "start": 3922,
                "duration": 0,
                "data": "https://www.fivebelow.com/_next/static/chunks/9359.221ace5a2e2806ed.js"
            },
            {
                "actionId": "1kygkf4rpox7t9hs",
                "type": "html/script",
                "start": 3933,
                "duration": 0,
                "data": "https://www.fivebelow.com/_next/static/chunks/webpack-8e0de439ca35877a.js"
            },
            {
                "actionId": "rjny1latjb12x0xs",
                "type": "html/script",
                "start": 3939,
                "duration": 0,
                "data": "https://www.fivebelow.com/_next/static/chunks/framework-945b357d4a851f4b.js"
            },
            {
                "actionId": "1ok3k12dsrn1g00mq",
                "type": "html/script",
                "start": 3945,
                "duration": 0,
                "data": "https://www.fivebelow.com/_next/static/chunks/main-3c4d521071d66a83.js"
            },
            {
                "actionId": "7oqr6e56sgowro9",
                "type": "html/script",
                "start": 3952,
                "duration": 0,
                "data": "https://www.fivebelow.com/_next/static/chunks/pages/_app-28984fb1b04ec1a9.js"
            },
            {
                "actionId": "vakn2lnaacjqm3v",
                "type": "page-load",
                "start": 3012,
                "duration": 1201.1999999999534,
                "stackTrace": [
                    "http://localhost:8001/script/internals:9067:20",
                    "https://www.fivebelow.com/:65:9"
                ]
            },
            {
                "actionId": "18lsnz3clhb1mu6i8",
                "type": "event/readystatechange/interactive",
                "start": 4227,
                "duration": 0,
                "stackTrace": [
                    "http://localhost:8001/script/internals:6815:24"
                ]
            },
            {
                "actionId": "8hiisrh6fc96rj",
                "type": "html/script",
                "start": 3959,
                "duration": 0,
                "data": "https://www.fivebelow.com/_next/static/chunks/29107295-4cc022cea922dbb4.js"
            },
            {
                "actionId": "1ejdgz1h4y7g2z9mz",
                "type": "html/script",
                "start": 4023,
                "duration": 0,
                "data": "https://www.fivebelow.com/.netlify/scripts/rum"
            },
            {
                "actionId": "3ac1m1e3dxbcyd6n",
                "type": "event/DOMContentLoaded",
                "start": 6043,
                "duration": 0,
                "stackTrace": [
                    "http://localhost:8001/script/internals:6803:24"
                ]
            },
            {
                "actionId": "xdh361h12vj1je4h2",
                "type": "document.cookie/read",
                "start": 17778,
                "duration": 0.09999999997671694,
                "stackTrace": [
                    "http://localhost:8001/script/internals:6677:24 [reportFopi]"
                ]
            },
            {
                "actionId": "1jcdj9us745hgv3h",
                "type": "event/readystatechange/complete",
                "start": 25696,
                "duration": 0,
                "stackTrace": [
                    "http://localhost:8001/script/internals:6815:24"
                ]
            },
            {
                "actionId": "oocxz1m7wif13crlg",
                "type": "event/load",
                "start": 25700,
                "duration": 0,
                "stackTrace": [
                    "http://localhost:8001/script/internals:6806:24"
                ]
            },
            {
                "actionId": "tosag1dud1b1b9sae",
                "type": "UnknownParentCreatingAction",
                "start": null,
                "duration": null,
                "data": null
            }
        ],
        "length": null,
        "savedScript": false
    }],
    "requests": [{
        "contentType": "application/json",
        "duration": 996,
        "method": "GET",
        "ip": "104.18.86.42",
        "requestSource": "fetch",
        "responseBodySize": 162759,
        "start": 8505,
        "status": 200,
        "id": "1a7wqybimgl4tgij",
        "statusMessage": "",
        "requestHeaders": {
            "Accept": "*/*",
            "Referer": "https://www.fivebelow.com/",
            "User-Agent": "Mozilla/5.0 (Windows NT 10.0; Win64; x64) AppleWebKit/537.36 (KHTML, like Gecko) Chrome/125.0.0.0 Safari/537.36",
            "sec-ch-ua": "\"Not)A;Brand\";v=\"8\", \"Chromium\";v=\"125\", \"Google Chrome\";v=\"125\"",
            "sec-ch-ua-mobile": "?0",
            "sec-ch-ua-platform": "\"Windows\""
        },
        "responseHeaders": {
            "date": "Wed, 03 Sep 2025 20:55:35 GMT",
            "content-type": "application/json",
            "server": "cloudflare",
            "cf-ray": "9798261bfd55c667-ORD",
            "cf-cache-status": "HIT",
            "accept-ranges": "bytes",
            "access-control-allow-origin": "*",
            "age": "27932",
            "cache-control": "public, max-age=86400",
            "content-encoding": "gzip",
            "etag": "0x8DD61731AD84C04",
            "expires": "Thu, 04 Sep 2025 20:55:35 GMT",
            "last-modified": "Wed, 12 Mar 2025 14:35:15 GMT",
            "strict-transport-security": "max-age=31536000; includeSubDomains; preload",
            "vary": "Accept-Encoding",
            "access-control-expose-headers": [
                "x-ms-request-id,Server,x-ms-version,Content-Type,Content-Encoding,Cache-Control,Last-Modified,ETag,Content-MD5,x-ms-lease-status,x-ms-blob-type,Content-Length,Date,Transfer-Encoding",
                "X-OneTrust-IsBot"
            ],
            "content-md5": "5Y5O1NEr2QMIRonO2KkoGg==",
            "cross-origin-resource-policy": "cross-origin",
            "x-content-type-options": "nosniff",
            "x-ms-blob-type": "BlockBlob",
            "x-ms-lease-status": "unlocked",
            "x-ms-request-id": "a663a29f-c01e-00f4-4742-ecb666000000",
            "x-ms-version": "2009-09-19",
            "x-onetrust-isbot": "true"
        },
        "responseHealthFlag": 1,
        "actionId": "1a7wqybimgl4tgij",
        "requestId": "1a7wqybimgl4tgij",
        "url": "https://cdn.cookielaw.org/consent/e42ebdfc-5934-4797-aee5-ba00806aba46/018e3318-931b-7244-8e0f-4d21cecab3c8/en.json"
    }],
    "cookies": [{
        "actionId": "1",
        "maxAge": 2147483646,
        "owner": "www.fivebelow.com",
        "key": "fs_visitorID_cookie",
        "value": "38ce5c66-510f-403a-ad43-c891432dc265",
        "expires": "Infinity",
        "domain": null,
        "path": "/",
        "secure": false,
        "httpOnly": false
    }],
    "links": [{
        "address": "https://www.fivebelow.com/#main-content",
        "framePartId": "1",
        "id": "90qdaavvxw14fouc"
    }],
    "timing": [],
    "yields": {
        "checkout-page-1": [
            "https://www.fivebelow.com/"
        ],
        "pci": [{
                "htmlType": "tel",
                "framePartId": "1",
                "htmlId": "cNumber",
                "htmlName": "f1j",
                "htmlClass": "inputModalLable form-control bio-input-text ",
                "htmlTag": "input",
                "form": null,
                "id": "15j613pyjg115mya1",
                "$type": "snapshot"
            },
            {
                "framePartId": "1",
                "htmlId": "exp_mmm",
                "htmlClass": "bio-input-text-select form-control inputModalLable ",
                "htmlTag": "select",
                "form": null,
                "id": "8v6z41763flhqez9",
                "$type": "snapshot"
            },
            {
                "framePartId": "1",
                "htmlId": "exp_yyy",
                "htmlClass": "bio-input-text-select form-control inputModalLable",
                "htmlTag": "select",
                "form": null,
                "id": "5cjt3cs39q1fqbaz",
                "$type": "snapshot"
            },
            {
                "htmlType": "tel",
                "framePartId": "1",
                "htmlId": "secCode",
                "htmlClass": "inputModalLable form-control bio-input-text width-75 height-39 ",
                "htmlTag": "input",
                "form": null,
                "id": "ybfwx16d9qn1gx55q",
                "$type": "snapshot"
            }
        ]
    },
    "sensitiveInputs": [{
        "id": "niylpdedoz1mvso4",
        "partId": "1",
        "sensitivityType": "sensitive",
        "data": "billing-email",
        "actionId": "o3svu1c26tx3ybwf",
        "element": {
            "htmlType": "email",
            "framePartId": "1",
            "htmlId": "billing-email",
            "htmlName": "email",
            "htmlClass": "h-50 focus:border-gray-500 focus:ring-0 w-full rounded-md border border-gray-400 px-10 text-gray-900 placeholder:text-14 placeholder:leading-normal placeholder:text-secondary-black focus:outline-none disabled:cursor-not-allowed disabled:bg-neutral-400 bg-white py-10   ",
            "htmlTag": "input",
            "form": null,
            "id": "81btu8zqcy19p8",
            "$type": "snapshot"
        }
    }],
    "commandsExecuted": [{
        "command": {
            "id": "AttachDebugger_1",
            "code": "AttachDebugger",
            "description": "AttachDebugger",
            "path": "/AttachDebugger",
            "traceId": "AttachDebugger_1"
        },
        "duration": 831.1029000000017,
        "id": "AttachDebugger_1",
        "pageId": "0",
        "start": 7458
    }]
}